MANIFEST.in
README.rst
setup.cfg
setup.py
lib/__init__.py
lib/_version.py
lib/agent.py
lib/auth.py
lib/decoders.py
lib/error.py
lib/log.py
lib/messages.py
lib/protocols.py
lib/proxy.py
lib/requester.py
lib/util.py
lib/cases/__init__.py
lib/cases/_test_comparison.py
lib/cases/_test_transfer.py
lib/cases/http_server.py
lib/cases/junk_server.py
lib/cases/md5_server.py
lib/cases/server.py
lib/cases/test_agent.py
lib/cases/test_auth.py
lib/cases/test_decoders.py
lib/cases/test_functional.py
lib/cases/test_http.py
lib/cases/test_jigsaw.py
lib/cases/test_proxy.py
lib/cases/util.py
pendrell.egg-info/PKG-INFO
pendrell.egg-info/SOURCES.txt
pendrell.egg-info/dependency_links.txt
pendrell.egg-info/top_level.txt