Metadata-Version: 1.1
Name: pendrell
Version: 0.3.4
Summary: HTTP 1.1 user agent for the programmable web
Home-page: http://pendrell.olix0r.net/
Author: Oliver Gould
Author-email: ver@olix0r.net
License: MIT
Platform: UNKNOWN
Classifier: Development Status :: 4 - Beta
Classifier: Environment :: Web Environment
Classifier: Framework :: Twisted
Classifier: Intended Audience :: Developers
Classifier: License :: OSI Approved :: MIT License
Classifier: Topic :: Internet :: WWW/HTTP
Requires: twisted.web
Provides: pendrell
